longyuanpower.py
longyuanpower-1.0.dist-info/LICENSE
longyuanpower-1.0.dist-info/METADATA
longyuanpower-1.0.dist-info/WHEEL
longyuanpower-1.0.dist-info/top_level.txt
longyuanpower-1.0.dist-info/RECORD
