Metadata-Version: 2.1
Name: longyuanpower
Version: 1.0
Summary: A module for turbine power prediction
Home-page: https://github.com/962516016/longyuanpower
Author: yuange_liu, daobin_luo
Author-email: liuyuange811@gmail.com, luodaobin2001@gmail.com
License: MIT
Classifier: Programming Language :: Python
Classifier: Programming Language :: Python :: 3
Classifier: Programming Language :: Python :: 3.5
Classifier: Programming Language :: Python :: 3.5
Classifier: Programming Language :: Python :: 3.6
Classifier: Programming Language :: Python :: 3.7
Classifier: Programming Language :: Python :: Implementation :: CPython
License-File: LICENSE
Requires-Dist: requests (<=2.31.0)
